LICENSE
MANIFEST.in
README.md
setup.cfg
setup.py
deps/pocketsphinx/include/cmdln_macro.h
deps/pocketsphinx/include/pocketsphinx.h
deps/pocketsphinx/include/pocketsphinx_export.h
deps/pocketsphinx/include/ps_lattice.h
deps/pocketsphinx/include/ps_mllr.h
deps/pocketsphinx/include/ps_search.h
deps/pocketsphinx/src/libpocketsphinx/acmod.c
deps/pocketsphinx/src/libpocketsphinx/acmod.h
deps/pocketsphinx/src/libpocketsphinx/allphone_search.c
deps/pocketsphinx/src/libpocketsphinx/allphone_search.h
deps/pocketsphinx/src/libpocketsphinx/bin_mdef.c
deps/pocketsphinx/src/libpocketsphinx/bin_mdef.h
deps/pocketsphinx/src/libpocketsphinx/blkarray_list.c
deps/pocketsphinx/src/libpocketsphinx/blkarray_list.h
deps/pocketsphinx/src/libpocketsphinx/dict.c
deps/pocketsphinx/src/libpocketsphinx/dict.h
deps/pocketsphinx/src/libpocketsphinx/dict2pid.c
deps/pocketsphinx/src/libpocketsphinx/dict2pid.h
deps/pocketsphinx/src/libpocketsphinx/fsg_history.c
deps/pocketsphinx/src/libpocketsphinx/fsg_history.h
deps/pocketsphinx/src/libpocketsphinx/fsg_lextree.c
deps/pocketsphinx/src/libpocketsphinx/fsg_lextree.h
deps/pocketsphinx/src/libpocketsphinx/fsg_search.c
deps/pocketsphinx/src/libpocketsphinx/fsg_search_internal.h
deps/pocketsphinx/src/libpocketsphinx/hmm.c
deps/pocketsphinx/src/libpocketsphinx/hmm.h
deps/pocketsphinx/src/libpocketsphinx/kws_detections.c
deps/pocketsphinx/src/libpocketsphinx/kws_detections.h
deps/pocketsphinx/src/libpocketsphinx/kws_search.c
deps/pocketsphinx/src/libpocketsphinx/kws_search.h
deps/pocketsphinx/src/libpocketsphinx/mdef.c
deps/pocketsphinx/src/libpocketsphinx/mdef.h
deps/pocketsphinx/src/libpocketsphinx/ms_gauden.c
deps/pocketsphinx/src/libpocketsphinx/ms_gauden.h
deps/pocketsphinx/src/libpocketsphinx/ms_mgau.c
deps/pocketsphinx/src/libpocketsphinx/ms_mgau.h
deps/pocketsphinx/src/libpocketsphinx/ms_senone.c
deps/pocketsphinx/src/libpocketsphinx/ms_senone.h
deps/pocketsphinx/src/libpocketsphinx/ngram_search.c
deps/pocketsphinx/src/libpocketsphinx/ngram_search.h
pocketsphinx_fork.egg-info/PKG-INFO
pocketsphinx_fork.egg-info/SOURCES.txt
pocketsphinx_fork.egg-info/dependency_links.txt
pocketsphinx_fork.egg-info/not-zip-safe
pocketsphinx_fork.egg-info/top_level.txt
