Metadata-Version: 2.1
Name: pocketsphinx-fork
Version: 1.0.0
Summary: Forked version of [pocketsphinx-python](https://github.com/bambocher/pocketsphinx-python) which adds utility for installing models, and the StreamSpeech interface.
Home-page: UNKNOWN
License: BSD
Keywords: sphinxbase pocketsphinx
Platform: UNKNOWN
Classifier: Development Status :: 2 - Pre-Alpha
Classifier: Operating System :: Microsoft :: Windows
Classifier: Operating System :: POSIX :: Linux
Classifier: Operating System :: MacOS
Classifier: License :: OSI Approved :: BSD License
Classifier: Programming Language :: Python :: 3.6
Classifier: Programming Language :: C
Classifier: Intended Audience :: Developers
Classifier: Topic :: Software Development :: Libraries :: Python Modules
Classifier: Topic :: Multimedia :: Sound/Audio :: Speech
